[
	{
		"fullArticle":"তারিখঃ ৭ ডিসেম্বর ২১             \nশিরোনামঃখাদ্য উৎপাদনের সাফল্য থেকে যেন ছিটকে না যাই\n\n#খাদ্য উৎপাদনের সাফল্য থেকে যেন ছিটকে না যাই\n\n• খাদ্য –food \n• উৎপাদন-production \n• খাদ্য উৎপাদন-food production \n• খাদ্য উৎপাদনের-of food production \n• সাফল্য-success \n• থেকে-from \n• যেন-as /like \n• ছিটকে যাওয়া- derail / off the track / goes off the flow / drop out / carry away \n• ছিটকে যাই-we are to derail / we derailed \n• ছিটকে না যাই – don’t dropped out / we don’t expect to drop out / don’t derail \n• সাফল্য থেকে যেন ছিটকে না যাই- don’t derail on the success \n• খাদ্য উৎপাদনের সাফল্য থেকে যেন ছিটকে না যাই- don’t derail on the success of food production / we expect no drop out on the success of the food production \n\n#জনসংখ্যার অত্যধিক ঘনত্ব, জমি-জন অনুপাতের অল্পতা ও চাষযোগ্য জমির ক্রমসংকোচন সত্ত্বেও বাংলাদেশ ধান উৎপাদনে স্বয়ম্ভরতা অর্জন করে এখন মোটা ধান-উদ্বৃত্ত দেশে পরিণত হয়েছে।\n\n• জনসংখ্যা-population \n• জনসংখ্যার-of the population \n• অত্যধিক - high\n• ঘনত্ব-density \n• অত্যধিক ঘনত্ব- high density\n• জনসংখ্যার অত্যধিক ঘনত্ব, - high density of the population/ high dense population\n• জমি-জন- land-to-population\n• অনুপাত-ratio \n• অনুপাতের-of the ratio\n• জমি-জন অনুপাতের- land-to-population ratio \n• অল্পতা –insufficiency / shortage / shortness \n• অনুপাতের অল্পতা – insufficiency of the ratio \n• জমি-জন অনুপাতের অল্পতা ও - insufficiency of the land-to-population ratio \n• চাষযোগ্য – arable/cultivable \n• জমি-land \n• চাষযোগ্য জমি- cultivable land \n• ক্রমসংকোচন – shrinkage/compression \n• চাষযোগ্য জমির ক্রমসংকোচন সত্ত্বেও –despite the compression of cultivable land \n• বাংলাদেশ-Bangladesh \n• ধান –paddy \n• উৎপাদন-production \n• ধান উৎপাদন- paddy production\n• ধান উৎপাদনে-in paddy production\n• স্বয়ম্ভরতা- self-sufficiency/ sufficiency \n• অর্জন করা-achieve \n• অর্জন করে- achieving \n• স্বয়ম্ভরতা অর্জন করে- achieving sufficiency \n• ধান উৎপাদনে স্বয়ম্ভরতা অর্জন করে - achieving sufficiency in paddy production \n• বাংলাদেশ ধান উৎপাদনে স্বয়ম্ভরতা অর্জন করে - achieving sufficiency in paddy production, Bangladesh \n• মোটা ধান-উদ্বৃত্ত-traditional paddy-surplus\n• পরিণত হয়েছে-has become \n• ধান-উদ্বৃত্ত দেশে পরিণত হয়েছে- has become traditional paddy-surplus country \n• এখন মোটা ধান-উদ্বৃত্ত দেশে পরিণত হয়েছে- has become traditional paddy-surplus country now \n• জনসংখ্যার অত্যধিক ঘনত্ব, জমি-জন অনুপাতের অল্পতা ও চাষযোগ্য জমির ক্রমসংকোচন- high dense population, insufficiency of the land-to-population ratio and the compression of cultivable land\n• জনসংখ্যার অত্যধিক ঘনত্ব, জমি-জন অনুপাতের অল্পতা ও চাষযোগ্য জমির ক্রমসংকোচন সত্ত্বেও- despite high dense population, insufficiency of the land-to-population ratio and the compression of cultivable land \n• জনসংখ্যার অত্যধিক ঘনত্ব, জমি-জন অনুপাতের অল্পতা ও চাষযোগ্য জমির ক্রমসংকোচন সত্ত্বেও বাংলাদেশ ধান উৎপাদনে স্বয়ম্ভরতা অর্জন করে- despite high dense population, insufficiency of the land-to-population ratio and the compression of cultivable land; achieving sufficiency in paddy production, Bangladesh \n• জনসংখ্যার অত্যধিক ঘনত্ব, জমি-জন অনুপাতের অল্পতা ও চাষযোগ্য জমির ক্রমসংকোচন সত্ত্বেও বাংলাদেশ ধান উৎপাদনে স্বয়ম্ভরতা অর্জন করে এখন মোটা ধান-উদ্বৃত্ত দেশে পরিণত হয়েছে- despite high dense population, insufficiency of the land-to-population ratio and the compression of cultivable land; achieving sufficiency in paddy production, now Bangladesh has become traditional paddy-surplus country \n\n#১৯৭২ সালে বাংলাদেশে ধান উৎপাদনের পরিমাণ ছিল মাত্র ১ কোটি ১০ লাখ টন, ২০২০ সালে তা সাড়ে তিন গুণ বেড়ে ৩ কোটি ৮২ লাখ টন ছাড়িয়ে গেছে।\n\n• ১৯৭২ সালে বাংলাদেশে ধান উৎপাদনের পরিমাণ ছিল মাত্র ১ কোটি ১০ লাখ টন- the production of paddy in Bangladesh was only 1.1 crore tons in 1972\n• ২০২০ সালে তা সাড়ে তিন গুণ বেড়ে ৩ কোটি ৮২ লাখ টন ছাড়িয়ে গেছে-which is multiplied three times and crosses 3.82 crore tons in 2020 \n• ১৯৭২ সালে বাংলাদেশে ধান উৎপাদনের পরিমাণ ছিল মাত্র ১ কোটি ১০ লাখ টন, ২০২০ সালে তা সাড়ে তিন গুণ বেড়ে ৩ কোটি ৮২ লাখ টন ছাড়িয়ে গেছে- the production of paddy in Bangladesh was only 1.1 crore tons in 1972 which is multiplied three times and crosses 3.82 crore tons in 2020 \n\n#মিঠাপানির মাছ উৎপাদনে বাংলাদেশ এখন বিশ্বে তৃতীয় স্থান অর্জন করেছে। তরিতরকারি উৎপাদনে বাংলাদেশ এখন বিশ্বে চতুর্থ।\n\n• মিঠাপানির মাছ উৎপাদনে বাংলাদেশ এখন বিশ্বে তৃতীয় স্থান অর্জন করেছে। তরিতরকারি উৎপাদনে বাংলাদেশ এখন বিশ্বে চতুর্থ-Bangladesh has secured third position now in producing fresh-water fish and also fourth position in vegetable production \n\n#Your Turn (Break-Translate-Rearrange)\nকৃষি খাতের সমৃদ্ধি বাংলাদেশের বৈশ্বিক ভাবমূর্তি বদলে ফেলার পেছনে সবচেয়ে বড় ভূমিকা পালন করে চলেছে।\n",
		"headLine1" : "খাদ্য উৎপাদনের সাফল্য থেকে যেন ছিটকে না যাই",
		"newsPaperName": "The Prothom alo ",
		"publishDate": "07-12-2021",
		"creditText" : "Prepared by: Mehedi "
	}
]
