[
	{
		"fullArticle":"তারিখঃ ৩১ ডিসেম্বর  ২১                   \nশিরোনামঃকরোনার এমন পরিস্থিতি আগে দেখেননি যুক্তরাষ্ট্রের বিশেষজ্ঞরা\n\n#করোনার এমন পরিস্থিতি আগে দেখেননি যুক্তরাষ্ট্রের বিশেষজ্ঞরা\n\n• করোনা-corona \n• করোনার-of corona / corona’s \n• এমন –such \n• পরিস্থিতি- situation\n• আগে-before \n• দেখা –see \n• দেখেন- saw \n• দেখেননি-didn’t see \n• যুক্তরাষ্ট্র - US\n• যুক্তরাষ্ট্রের  -of US \n• বিশেষজ্ঞরা- experts\n• যুক্তরাষ্ট্রের বিশেষজ্ঞরা- experts of US / US experts \n• দেখেননি যুক্তরাষ্ট্রের বিশেষজ্ঞরা- US experts didn’t see \n• আগে দেখেননি যুক্তরাষ্ট্রের বিশেষজ্ঞরা- US experts didn’t see before \n• এমন পরিস্থিতি আগে দেখেননি যুক্তরাষ্ট্রের বিশেষজ্ঞরা- US experts didn’t such situation see before \n• করোনার এমন পরিস্থিতি আগে দেখেননি যুক্তরাষ্ট্রের বিশেষজ্ঞরা- US experts didn’t such a situation of corona see before\n\n# যুক্তরাষ্ট্রে করোনাভাইরাসের মহামারির ঢেউ এর আগেও আঘাত হেনেছে।\n\n• যুক্তরাষ্ট্র-US \n• যুক্তরাষ্ট্রে-in US\n• করোনাভাইরাস- corona virus \n• করোনাভাইরাসের –of corona virus \n• মহামারি-pandemic \n• মহামারির-of the pandemic \n• ঢেউ-wave \n• মহামারির ঢেউ- wave of the pandemic / the pandemic wave \n• করোনাভাইরাসের মহামারির ঢেউ- the pandemic wave of corona virus / wave of the pandemic of corona virus \n• যুক্তরাষ্ট্রে করোনাভাইরাসের মহামারির ঢেউ - the pandemic wave of corona virus in US \n• এর-this \n• আগেও –before /earlier \n• এর আগেও- before this \n• আঘাত হানা –hit \n• আঘাত হেনেছে-has hit \n• এর আগেও আঘাত হেনেছে- has hit before this  \n• যুক্তরাষ্ট্রে করোনাভাইরাসের মহামারির ঢেউ এর আগেও আঘাত হেনেছে- the pandemic wave of corona virus has hit before this  in US  \n\n#তবে সম্প্রতি যেভাবে সংক্রমণ বাড়ছে তা আগে দেখেননি বিশেষজ্ঞরা।\n\n• বিশেষজ্ঞরা-experts \n• দেখেননি বিশেষজ্ঞরা- experts didn’t see \n• আগে দেখেননি বিশেষজ্ঞরা- experts didn’t see before \n• তা আগে দেখেননি বিশেষজ্ঞরা- experts didn’t see this before \n• বাড়ছে তা আগে দেখেননি বিশেষজ্ঞরা- experts didn’t see this before, increasing \n• সংক্রমণ বাড়ছে তা আগে দেখেননি বিশেষজ্ঞরা- experts didn’t see before infection is increasing  \n• যেভাবে সংক্রমণ বাড়ছে তা আগে দেখেননি বিশেষজ্ঞরা- experts didn’t see before how infection is increasing  \n• সম্প্রতি যেভাবে সংক্রমণ বাড়ছে তা আগে দেখেননি বিশেষজ্ঞরা - experts didn’t see before how infection is increasing this time \n• তবে সম্প্রতি যেভাবে সংক্রমণ বাড়ছে তা আগে দেখেননি বিশেষজ্ঞরা-but experts didn’t see before how infection is increasing this time \n\n#চিকিৎসকেরা বলছেন, দেশটির হাসপাতালগুলোর জরুরি বিভাগের কক্ষগুলো সব সময় ভর্তি থাকছে রোগীতে।\n\n• চিকিৎসকেরা বলছেন, - Doctors say \n• দেশটির হাসপাতালগুলোর জরুরি বিভাগের কক্ষগুলো- the emergency department rooms of the hospitals in the country \n• সব সময় ভর্তি থাকছে রোগীতে- always full of patients \n• চিকিৎসকেরা বলছেন, দেশটির হাসপাতালগুলোর জরুরি বিভাগের কক্ষগুলো- Doctors say the emergency department rooms of the hospitals in the country \n• চিকিৎসকেরা বলছেন, দেশটির হাসপাতালগুলোর জরুরি বিভাগের কক্ষগুলো সব সময় ভর্তি থাকছে রোগীতে- Doctors say the emergency department rooms of the hospitals in the country are always full of patients \n\n#করোনা পরিস্থিতি সামাল দিতে বিশেষজ্ঞরা আহ্বান জানাচ্ছেন, নতুন বছরের শুরুর উদ্যাপনের আয়োজন যতটা সম্ভব সংক্ষিপ্ত করুন।\n\n• করোনা পরিস্থিতি সামাল দিতে বিশেষজ্ঞরা আহ্বান জানাচ্ছেন, নতুন বছরের শুরুর উদ্যাপনের আয়োজন যতটা সম্ভব সংক্ষিপ্ত করুন-Experts are calling upon to curve the new year celebration as much as possible for the sake of dealing with corona situation   \n\n#Your Turn (Break-Translate-Rearrange)\nযাদের হাসপাতালে নেওয়া হচ্ছে তাদের অধিকাংশই টিকা নেননি।\n",
		"headLine1" : "করোনার এমন পরিস্থিতি আগে দেখেননি যুক্তরাষ্ট্রের বিশেষজ্ঞরা",
		"newsPaperName": "Prothomalo ",
		"publishDate": "31-12-2021",
		"creditText" : "Prepared by: Mehedi "
	}, 
	{
		"fullArticle":"Date: 31 December 21 \nHeading: World must heed WHO’s warning about Omicron\n \n#World must heed WHO’s warning about Omicron\n\n• World – বিশ্ব \n• must-অবশ্যই \n• World must- বিশ্ব অবশ্যই\n• Heed-মানা /  মনযোগ দেওয়া / লক্ষ করা \n• World must heed-  বিশ্বকে অবশ্যই মনযোগ দিতে হবে \n• WHO- বিশ্ব স্বাস্থ্য সংস্থা \n• WHO’s- বিশ্ব স্বাস্থ্য সংস্থার \n• Warning- সতর্কতা \n• WHO’s warning- বিশ্ব স্বাস্থ্য সংস্থার সতর্কতা \n• about –সম্পর্কে \n• Omicron-ওমিক্রন \n• about Omicron- ওমিক্রন সম্পর্কে \n• WHO’s warning about Omicron- ওমিক্রন সম্পর্কে বিশ্ব স্বাস্থ্য সংস্থার সতর্কতা \n• World must heed WHO’s warning about Omicron- বিশ্বকে অবশ্যই ওমিক্রন সম্পর্কে বিশ্ব স্বাস্থ্য সংস্থার সতর্কতার প্রতি মনযোগ দিতে হবে \n\n#Bangladesh should also prepare its healthcare system for any case surges\n\n• Bangladesh – বাংলাদেশ \n• should –উচিৎ \n• also –আরও /এছাড়া \n• prepare –প্রস্তুত করা \n• Bangladesh should also prepare – বাংলাদেশেরও প্রস্তুত করা উচিৎ \n• Its –এর \n• healthcare – স্বাস্থ্যসেবা \n• system-ব্যবস্থা \n• healthcare system- স্বাস্থ্যসেবা ব্যবস্থা\n• its healthcare system- এর স্বাস্থ্যসেবা ব্যবস্থা\n• for –জন্য \n• any –যেকোনো \n• case –অবস্থা / বিষয়াদি \n• surges-বৃদ্ধি ঘটে \n• case surges- অবস্থার বৃদ্ধি ঘটে \n• for any case surges-কোন অবস্থার বৃদ্ধিতে  \n• its healthcare system for any case surges- কোন অবস্থার বৃদ্ধিতে  এর স্বাস্থ্যসেবা ব্যবস্থা\n• Bangladesh should also prepare its healthcare system for any case surges- বাংলাদেশেরও যেকোনো অবস্থার বৃদ্ধির ক্ষেত্রে এর স্বাস্থ্যসেবা ব্যবস্থা প্রস্তুত করা উচিৎ    \n\n#As many countries around the world have been experiencing fresh surges in Covid-19 cases–propelled by the highly transmissible Omicron variant–and have brought back restrictions to curb further spread of the infections, Bangladesh should also take necessary preparations to deal with any fresh surge of infections.\n\n• As many countries around the world –যেহেতু পৃথিবীজুড়ে অনেক দেশ \n• have been experiencing fresh surges in Covid-19 cases–কোভিড – ১৯ এর নতুন ঢেউয়ের সম্মুখীন হচ্ছে\n• propelled by the highly transmissible Omicron variant– অত্যধিক সংক্রমণযোগ্য ওমিক্রন  দ্বারা চালিত হয়েছে-\n• and have brought back restrictions – এবং বিধিনিষেধ ফিরিয়ে আনা হয়েছে \n• to curb further spread of the infections, - বিস্তার কমানোর জন্য\n• Bangladesh should also take necessary preparations - বাংলাদেশেরও প্রয়োজনীয় প্রস্তুতি নেওয়া উচিত \n• to deal with any fresh surge of infections- নতুন ঢেউ মোকাবেলায়\n• As many countries around the world have been experiencing fresh surges in Covid-19 cases– যেহেতু পৃথিবীজুড়ে অনেক দেশ কোভিড – ১৯ এর নতুন ঢেউয়ের সম্মুখীন হচ্ছে \n• As many countries around the world have been experiencing fresh surges in Covid-19 cases–propelled by the highly transmissible Omicron variant– যেহেতু পৃথিবীজুড়ে অনেক দেশ কোভিড – ১৯ এর নতুন ঢেউয অত্যধিক সংক্রমণযোগ্য ওমিক্রনের সম্মুখীন হচ্ছে  \n• As many countries around the world have been experiencing fresh surges in Covid-19 cases–propelled by the highly transmissible Omicron variant–and have brought back restrictions to curb further spread of the infections- যেহেতু পৃথিবীজুড়ে অনেক দেশ কোভিড – ১৯ এর নতুন ঢেউয অত্যধিক সংক্রমণযোগ্য ওমিক্রনের সম্মুখীন হচ্ছে  এবং বিস্তার কমানোর জন্য বিধিনিষেধ ফিরিয়ে আনা হয়েছে \n• As many countries around the world have been experiencing fresh surges in Covid-19 cases–propelled by the highly transmissible Omicron variant–and have brought back restrictions to curb further spread of the infections, Bangladesh should also take necessary preparations- যেহেতু পৃথিবীজুড়ে অনেক দেশ কোভিড – ১৯ এর নতুন ঢেউয অত্যধিক সংক্রমণযোগ্য ওমিক্রনের সম্মুখীন হচ্ছে  এবং বিস্তার কমানোর জন্য বিধিনিষেধ ফিরিয়ে আনা হয়েছে , বাংলাদেশেরও প্রয়োজনীয় প্রস্তুতি নেওয়া উচিত \n• As many countries around the world have been experiencing fresh surges in Covid-19 cases–propelled by the highly transmissible Omicron variant–and have brought back restrictions to curb further spread of the infections, Bangladesh should also take necessary preparations to deal with any fresh surge of infections- যেহেতু পৃথিবীজুড়ে অনেক দেশ কোভিড – ১৯ এর নতুন ঢেউ অত্যধিক সংক্রমণযোগ্য ওমিক্রনের সম্মুখীন হচ্ছে  এবং বিস্তার কমানোর জন্য বিধিনিষেধ ফিরিয়ে আনা হয়েছে ,তাই নতুন ঢেউ মোকাবেলায় বাংলাদেশেরও প্রয়োজনীয় প্রস্তুতি নেওয়া উচিত \n\n#Reportedly, the WHO has warned the world about the threat Omicron poses, saying that it may lead to overwhelmed healthcare systems worldwide.\n\n• Reportedly, the WHO has warned the world about the threat Omicron poses, saying that it may lead to overwhelmed healthcare systems worldwide- প্রতিবেদনে অনুসারে, বিশ্ব স্বাস্থ্য সংস্থা বিশ্বকে ওমিক্রনের হুমকি সম্পর্কে সতর্ক করেছে এবং বলছে যে এটি বিশ্বব্যাপী স্বাস্থ্যসেবা ব্যবস্থাকে বিপর্যস্ত করতে পারে \n\n#(Break-Translate-Rearrange) \nEven though early studies suggest that Omicron leads to milder disease, China and Germany have already brought back tough restrictions to prevent new infections caused by this variant.\n",
		"headLine1" : "World must heed WHO’s warning about Omicron",
		"newsPaperName": "Daily Star ",
		"publishDate": "31-12-2021",
		"creditText" : "Prepared by: Mehedi "
	}

]
